Workbook
Name スライサー_担当者: #N/A

Sheet ショートカットキー①
A1: ①Ctrl + A（全選択)、Ctrl + C（コピー）、Ctrl + V（ペースト）
A3: 日付 | B3: 氏名 | C3: 契約プラン | F3: 日付 | G3: 氏名 | H3: 契約プラン
A4: 45606 | B4: 田中一郎 | C4: プランA | F4: 45606 | G4: 田中一郎 | H4: プランA
A5: 45607 | B5: 鈴木次郎 | C5: プランB | F5: 45607 | G5: 鈴木次郎 | H5: プランB
A6: 45608 | B6: 松本三郎 | C6: プランC | F6: 45608 | G6: 松本三郎 | H6: プランC
A7: 45609 | B7: 佐藤四郎 | C7: プランD | F7: 45609 | G7: 佐藤四郎 | H7: プランD
A8: 45610 | B8: 兼本五郎 | C8: プランE | F8: 45610 | G8: 兼本五郎 | H8: プランE
A11: ②Ctrl +D（上をコピー)
A12: 日付 | B12: 氏名 | C12: 契約プラン
A13: 45606 | B13: 田中一郎 | C13: プランA
A14: 45607 | B14: 鈴木次郎 | C14: プランB
A15: 45608 | B15: 松本五郎 | C15: プランC
A16: 45608 | B16: 松本三郎 | C16: プランC
A17: 45608 | B17: 松本三郎 | C17: プランC
A19: ③Ctrl + F（検索）、Ctrl ＋H（置換）
A20: 日付 | B20: 氏名 | C20: 契約プラン
A21: 45606 | B21: 田中一郎 | C21: プランA
A22: 45607 | B22: 鈴木次郎 | C22: プランB
A23: 45608 | B23: 松本三郎 | C23: プランC
A26: ④Ctrl + Shift + L（フィルター）
A27: 日付 | B27: 氏名 | C27: 契約プラン
A28: 45606 | B28: 田中一郎 | C28: プランA
A29: 45607 | B29: 鈴木次郎 | C29: プランB
A30: 45608 | B30: 松本三郎 | C30: プランC
A31: 45609 | B31: 佐藤四郎 | C31: プランA
A32: 45610 | B32: 兼本五郎 | C32: プランB

Sheet ショートカットキー②
A1: ⑤Ctrl + 1(表示形式）
A3: 日付 | B3: 売上
A4: 45606 | B4: 2000
A5: 45607 | B5: 1000
A6: 45608 | B6: 800
A7: 45609 | B7: 5000
A8: 45610 | B8: 3000
A11: ⑥Shift + マウス（セル範囲移動）
A12: 日付 | B12: 商品名 | C12: 売上
A13: 45606 | B13: A | C13: 2000
A14: 45607 | B14: B | C14: 1000
A15: 45608 | B15: C | C15: 800
A16: 45609 | B16: D | C16: 5000
A17: 45610 | B17: E | C17: 3000
A19: ⑦Ctrl ＋G（ジャンプ）、Ctrl + Enter（選択セルへ一括入力）
A20: 日付 | B20: 売上 | C20: 商品名
A21: 45606 | B21: 2000 | C21: A
A22: 45607 | B22: - | C22: B
A23: 45608 | B23: 800 | C23: -
A24: 45609 | B24: 5000 | C24: D
A25: 45610 | B25: - | C25: E
A27: ⑧Win + Shift + S（部分スクショ）
A30: ⑨Win + ←（画面半分表示）
A32: ⑩Ctrl + PageUP（またはPageDown)

Sheet ショートカットキー③
A1: ⑪Ctrl + - / Ctrl Shift + +（行列削除、行列追加）
A4: 日付 | B4: 氏名 | C4: 契約プラン
A5: 45606 | B5: 田中太郎 | C5: プランA
A6: 45607 | B6: 鈴木次郎 | C6: プランB
A7: 45608 | B7: 松本三郎 | C7: プランC
A8: 45609 | B8: 佐藤四郎 | C8: プランD
A9: 45610 | B9: 兼本五郎 | C9: プランE
A11: ⑫Ctrl + Shift + マウススクロール（横スクロール）
A13: 列1 | B13: 列2 | C13: 列3 | D13: 列4 | E13: 列5 | F13: 列6 | G13: 列7 | H13: 列8 | I13: 列9 | J13: 列10 | K13: 列11 | L13: 列12 | M13: 列13 | N13: 列14 | O13: 列15 | P13: 列16 | Q13: 列17 | R13: 列18 | S13: 列19 | T13: 列20 | U13: 列21 | V13: 列22 | W13: 列23 | X13: 列24 | Y13: 列25 | Z13: 列26 | AA13: 列27 | AB13: 列28 | AC13: 列29 | AD13: 列30 | AE13: 列31 | AF13: 列32 | AG13: 列33 | AH13: 列34 | AI13: 列35 | AJ13: 列36 | AK13: 列37 | AL13: 列38 | AM13: 列39 | AN13: 列40 | AO13: 列41 | AP13: 列42 | AQ13: 列43 | AR13: 列44 | AS13: 列45 | AT13: 列46 | AU13: 列47 | AV13: 列48 | AW13: 列49 | AX13: 列50 | AY13: 列51 | AZ13: 列52 | BA13: 列53 | BB13: 列54 | BC13: 列55 | BD13: 列56 | BE13: 列57 | BF13: 列58 | BG13: 列59 | BH13: 列60 | BI13: 列61 | BJ13: 列62 | BK13: 列63 | BL13: 列64 | BM13: 列65 | BN13: 列66 | BO13: 列67
A14: 123 | B14: 123 | C14: 123 | D14: 123 | E14: 123 | F14: 123 | G14: 123 | H14: 123 | I14: 123 | J14: 123 | K14: 123 | L14: 123 | M14: 123 | N14: 123 | O14: 123 | P14: 123 | Q14: 123 | R14: 123 | S14: 123 | T14: 123 | U14: 123 | V14: 123 | W14: 123 | X14: 123 | Y14: 123 | Z14: 123 | AA14: 123 | AB14: 123 | AC14: 123 | AD14: 123 | AE14: 123 | AF14: 123 | AG14: 123 | AH14: 123 | AI14: 123 | AJ14: 123 | AK14: 123 | AL14: 123 | AM14: 123 | AN14: 123 | AO14: 123 | AP14: 123 | AQ14: 123 | AR14: 123 | AS14: 123 | AT14: 123 | AU14: 123 | AV14: 123 | AW14: 123 | AX14: 123 | AY14: 123 | AZ14: 123 | BA14: 123 | BB14: 123 | BC14: 123 | BD14: 123 | BE14: 123 | BF14: 123 | BG14: 123 | BH14: 123 | BI14: 123 | BJ14: 123 | BK14: 123 | BL14: 123 | BM14: 123 | BN14: 123 | BO14: 123
A15: 123 | B15: 123 | C15: 123 | D15: 123 | E15: 123 | F15: 123 | G15: 123 | H15: 123 | I15: 123 | J15: 123 | K15: 123 | L15: 123 | M15: 123 | N15: 123 | O15: 123 | P15: 123 | Q15: 123 | R15: 123 | S15: 123 | T15: 123 | U15: 123 | V15: 123 | W15: 123 | X15: 123 | Y15: 123 | Z15: 123 | AA15: 123 | AB15: 123 | AC15: 123 | AD15: 123 | AE15: 123 | AF15: 123 | AG15: 123 | AH15: 123 | AI15: 123 | AJ15: 123 | AK15: 123 | AL15: 123 | AM15: 123 | AN15: 123 | AO15: 123 | AP15: 123 | AQ15: 123 | AR15: 123 | AS15: 123 | AT15: 123 | AU15: 123 | AV15: 123 | AW15: 123 | AX15: 123 | AY15: 123 | AZ15: 123 | BA15: 123 | BB15: 123 | BC15: 123 | BD15: 123 | BE15: 123 | BF15: 123 | BG15: 123 | BH15: 123 | BI15: 123 | BJ15: 123 | BK15: 123 | BL15: 123 | BM15: 123 | BN15: 123 | BO15: 123
A16: 123 | B16: 123 | C16: 123 | D16: 123 | E16: 123 | F16: 123 | G16: 123 | H16: 123 | I16: 123 | J16: 123 | K16: 123 | L16: 123 | M16: 123 | N16: 123 | O16: 123 | P16: 123 | Q16: 123 | R16: 123 | S16: 123 | T16: 123 | U16: 123 | V16: 123 | W16: 123 | X16: 123 | Y16: 123 | Z16: 123 | AA16: 123 | AB16: 123 | AC16: 123 | AD16: 123 | AE16: 123 | AF16: 123 | AG16: 123 | AH16: 123 | AI16: 123 | AJ16: 123 | AK16: 123 | AL16: 123 | AM16: 123 | AN16: 123 | AO16: 123 | AP16: 123 | AQ16: 123 | AR16: 123 | AS16: 123 | AT16: 123 | AU16: 123 | AV16: 123 | AW16: 123 | AX16: 123 | AY16: 123 | AZ16: 123 | BA16: 123 | BB16: 123 | BC16: 123 | BD16: 123 | BE16: 123 | BF16: 123 | BG16: 123 | BH16: 123 | BI16: 123 | BJ16: 123 | BK16: 123 | BL16: 123 | BM16: 123 | BN16: 123 | BO16: 123
A17: 123 | B17: 123 | C17: 123 | D17: 123 | E17: 123 | F17: 123 | G17: 123 | H17: 123 | I17: 123 | J17: 123 | K17: 123 | L17: 123 | M17: 123 | N17: 123 | O17: 123 | P17: 123 | Q17: 123 | R17: 123 | S17: 123 | T17: 123 | U17: 123 | V17: 123 | W17: 123 | X17: 123 | Y17: 123 | Z17: 123 | AA17: 123 | AB17: 123 | AC17: 123 | AD17: 123 | AE17: 123 | AF17: 123 | AG17: 123 | AH17: 123 | AI17: 123 | AJ17: 123 | AK17: 123 | AL17: 123 | AM17: 123 | AN17: 123 | AO17: 123 | AP17: 123 | AQ17: 123 | AR17: 123 | AS17: 123 | AT17: 123 | AU17: 123 | AV17: 123 | AW17: 123 | AX17: 123 | AY17: 123 | AZ17: 123 | BA17: 123 | BB17: 123 | BC17: 123 | BD17: 123 | BE17: 123 | BF17: 123 | BG17: 123 | BH17: 123 | BI17: 123 | BJ17: 123 | BK17: 123 | BL17: 123 | BM17: 123 | BN17: 123 | BO17: 123
A18: 123 | B18: 123 | C18: 123 | D18: 123 | E18: 123 | F18: 123 | G18: 123 | H18: 123 | I18: 123 | J18: 123 | K18: 123 | L18: 123 | M18: 123 | N18: 123 | O18: 123 | P18: 123 | Q18: 123 | R18: 123 | S18: 123 | T18: 123 | U18: 123 | V18: 123 | W18: 123 | X18: 123 | Y18: 123 | Z18: 123 | AA18: 123 | AB18: 123 | AC18: 123 | AD18: 123 | AE18: 123 | AF18: 123 | AG18: 123 | AH18: 123 | AI18: 123 | AJ18: 123 | AK18: 123 | AL18: 123 | AM18: 123 | AN18: 123 | AO18: 123 | AP18: 123 | AQ18: 123 | AR18: 123 | AS18: 123 | AT18: 123 | AU18: 123 | AV18: 123 | AW18: 123 | AX18: 123 | AY18: 123 | AZ18: 123 | BA18: 123 | BB18: 123 | BC18: 123 | BD18: 123 | BE18: 123 | BF18: 123 | BG18: 123 | BH18: 123 | BI18: 123 | BJ18: 123 | BK18: 123 | BL18: 123 | BM18: 123 | BN18: 123 | BO18: 123
A19: 123 | B19: 123 | C19: 123 | D19: 123 | E19: 123 | F19: 123 | G19: 123 | H19: 123 | I19: 123 | J19: 123 | K19: 123 | L19: 123 | M19: 123 | N19: 123 | O19: 123 | P19: 123 | Q19: 123 | R19: 123 | S19: 123 | T19: 123 | U19: 123 | V19: 123 | W19: 123 | X19: 123 | Y19: 123 | Z19: 123 | AA19: 123 | AB19: 123 | AC19: 123 | AD19: 123 | AE19: 123 | AF19: 123 | AG19: 123 | AH19: 123 | AI19: 123 | AJ19: 123 | AK19: 123 | AL19: 123 | AM19: 123 | AN19: 123 | AO19: 123 | AP19: 123 | AQ19: 123 | AR19: 123 | AS19: 123 | AT19: 123 | AU19: 123 | AV19: 123 | AW19: 123 | AX19: 123 | AY19: 123 | AZ19: 123 | BA19: 123 | BB19: 123 | BC19: 123 | BD19: 123 | BE19: 123 | BF19: 123 | BG19: 123 | BH19: 123 | BI19: 123 | BJ19: 123 | BK19: 123 | BL19: 123 | BM19: 123 | BN19: 123 | BO19: 123
A20: 123 | B20: 123 | C20: 123 | D20: 123 | E20: 123 | F20: 123 | G20: 123 | H20: 123 | I20: 123 | J20: 123 | K20: 123 | L20: 123 | M20: 123 | N20: 123 | O20: 123 | P20: 123 | Q20: 123 | R20: 123 | S20: 123 | T20: 123 | U20: 123 | V20: 123 | W20: 123 | X20: 123 | Y20: 123 | Z20: 123 | AA20: 123 | AB20: 123 | AC20: 123 | AD20: 123 | AE20: 123 | AF20: 123 | AG20: 123 | AH20: 123 | AI20: 123 | AJ20: 123 | AK20: 123 | AL20: 123 | AM20: 123 | AN20: 123 | AO20: 123 | AP20: 123 | AQ20: 123 | AR20: 123 | AS20: 123 | AT20: 123 | AU20: 123 | AV20: 123 | AW20: 123 | AX20: 123 | AY20: 123 | AZ20: 123 | BA20: 123 | BB20: 123 | BC20: 123 | BD20: 123 | BE20: 123 | BF20: 123 | BG20: 123 | BH20: 123 | BI20: 123 | BJ20: 123 | BK20: 123 | BL20: 123 | BM20: 123 | BN20: 123 | BO20: 123
A21: 123 | B21: 123 | C21: 123 | D21: 123 | E21: 123 | F21: 123 | G21: 123 | H21: 123 | I21: 123 | J21: 123 | K21: 123 | L21: 123 | M21: 123 | N21: 123 | O21: 123 | P21: 123 | Q21: 123 | R21: 123 | S21: 123 | T21: 123 | U21: 123 | V21: 123 | W21: 123 | X21: 123 | Y21: 123 | Z21: 123 | AA21: 123 | AB21: 123 | AC21: 123 | AD21: 123 | AE21: 123 | AF21: 123 | AG21: 123 | AH21: 123 | AI21: 123 | AJ21: 123 | AK21: 123 | AL21: 123 | AM21: 123 | AN21: 123 | AO21: 123 | AP21: 123 | AQ21: 123 | AR21: 123 | AS21: 123 | AT21: 123 | AU21: 123 | AV21: 123 | AW21: 123 | AX21: 123 | AY21: 123 | AZ21: 123 | BA21: 123 | BB21: 123 | BC21: 123 | BD21: 123 | BE21: 123 | BF21: 123 | BG21: 123 | BH21: 123 | BI21: 123 | BJ21: 123 | BK21: 123 | BL21: 123 | BM21: 123 | BN21: 123 | BO21: 123

Sheet ショートカットキー④
A1: ⑬Alt → H → O→I
A3: 売上日 | B3: 商品名 | C3: 個数 | D3: 売上
A4: 45597 | B4: Tシャツ | C4: 30 | D4: 20000
A5: 45598 | B5: ヘッドホン | C5: 20 | D5: 104000
A6: 45599 | B6: チョコレート | C6: 25 | D6: 4000
A7: 45600 | B7: ボールペン | C7: 13 | D7: 1500
A8: 45601 | B8: ランニングシューズ | C8: 14 | D8: 144000
A9: 45602 | B9: Tシャツ | C9: 28 | D9: 20000
A10: 45603 | B10: ボールペン | C10: 18 | D10: 900
A11: 45604 | B11: ランニングシューズ | C11: 30 | D11: 168000
A12: 45605 | B12: ヘッドホン | C12: 15 | D12: 88000
A13: 45606 | B13: チョコレート | C13: 18 | D13: 6500

Sheet 表示形式
A7: 和暦表示と桁区切り表示
A8: 日付 | B8: 売上
A9: 45606 | B9: 2000
A10: 45607 | B10: 1000
A11: 45608 | B11: 800
A12: 45609 | B12: 5000
A13: 45610 | B13: 3000

Sheet データの入力規則
A1: 日付 | B1: 氏名 | C1: 契約プラン
A2: 45606 | B2: 田中太郎 | C2: プランA
A3: 45607 | B3: 鈴木次郎 | C3: プランB
A4: 45608 | B4: 松本三郎 | C4: プランC
A5: 45609 | B5: 佐藤四郎 | C5: プランD
A6: 45610 | B6: 兼本五郎 | C6: プランE
C7: プランC
C9: プランD

Sheet プランリスト
A1: 契約プラン
A2: プランA
A3: プランB
A4: プランC
A5: プランD
A6: プランE

Sheet フラッシュフィル
A1: メール | B1: @より前 | C1: @あと
A2: sampleuser001@example.com | B2: sampleuser001 | C2: example.com
A3: sampleuser002@example.com | B3: sampleuser002 | C3: example.com
A4: sampleuser003@example.com | B4: sampleuser003 | C4: example.com
A5: sampleuser004@example.com | B5: sampleuser004 | C5: example.com
A6: sampleuser005@example.com | B6: sampleuser005 | C6: example.com
A7: sampleuser006@example.com | B7: sampleuser006 | C7: example.com
A8: tempaddress007@example.com | B8: tempaddress007 | C8: example.com
A9: mailtest008@example.com | B9: mailtest008 | C9: example.com
A10: userdemo009@example.com | B10: userdemo009 | C10: example.com
A11: trialuser010@example.com | B11: trialuser010 | C11: example.com
A12: newtest011@example.com | B12: newtest011 | C12: example.com
... A21: tempuser020@example.com | B21: tempuser020 | C21: example.com

Sheet SUM
A1: 日付 | B1: 売上 | D1: 合計
A2: 45606 | B2: 2000 | D2: =SUM(B2:B6) -> 11800
A3: 45607 | B3: 1000
A4: 45608 | B4: 800
A5: 45609 | B5: 5000
A6: 45610 | B6: 3000

Sheet IF
A1: 月 | B1: 目標 | C1: 実績 | D1: 達成状況
A2: 4 | B2: 100000 | C2: 98000 | D2: =IF(B2<C2, "達成", "未達") -> 未達 | F2: IF(式, 式が正しい場合, 式が間違っている場合)
A3: 5 | B3: 120000 | C3: 115000 | D3: =IF(B3<C3, "達成", "未達") -> 未達
A4: 6 | B4: 150000 | C4: 148000 | D4: =IF(B4<C4, "達成", "未達") -> 未達 | F4: =IF(B2<C2, "達成", "未達") -> 未達
A5: 7 | B5: 128000 | C5: 130000 | D5: =IF(B5<C5, "達成", "未達") -> 達成
A6: 8 | B6: 140000 | C6: 135000 | D6: =IF(B6<C6, "達成", "未達") -> 未達
A7: 9 | B7: 158000 | C7: 160000 | D7: =IF(B7<C7, "達成", "未達") -> 達成
A8: 10 | B8: 170000 | C8: 165000 | D8: =IF(B8<C8, "達成", "未達") -> 未達
A9: 11 | B9: 180000 | C9: 175000 | D9: =IF(B9<C9, "達成", "未達") -> 未達
A10: 12 | B10: 185000 | C10: 190000 | D10: =IF(B10<C10, "達成", "未達") -> 達成
A11: 1 | B11: 110000 | C11: 105000 | D11: =IF(B11<C11, "達成", "未達") -> 未達
A12: 2 | B12: 120000 | C12: 118000 | D12: =IF(B12<C12, "達成", "未達") -> 未達
A13: 3 | B13: 130000 | C13: 128000 | D13: =IF(B13<C13, "達成", "未達") -> 未達

Sheet VLOOKUP①
A1: 社員ID | B1: 氏名 | C1: 部署 | E1: 社員ID | F1: 氏名 | G1: 部署
A2: S0001 | B2: 田中太郎 | C2: 総務部 | E2: S0001 | F2: =VLOOKUP($E$2,$A$2:$C$6,2,FALSE) -> 田中太郎 | G2: =VLOOKUP($E$2,$A$2:$C$6,3,FALSE) -> 総務部
A3: S0002 | B3: 鈴木次郎 | C3: 経理部
A4: S0003 | B4: 松本三郎 | C4: IT部
A5: S0004 | B5: 佐藤四郎 | C5: 法務部
A6: S0005 | B6: 兼本五郎 | C6: 営業部

Sheet VLOOKUP②
A1: 売上日 | B1: 商品ID | C1: カテゴリー | D1: 商品名 | E1: 単価 | F1: 個数 | G1: 売上
A2: 45597 | B2: SH001 | C2: =VLOOKUP($B2, 商品マスタ!$A:$D, 2, FALSE) -> ファッション | D2: =VLOOKUP($B2, 商品マスタ!$A:$D, 3, FALSE) -> Tシャツ | E2: =VLOOKUP($B2, 商品マスタ!$A:$D, 4, FALSE) -> 2000 | F2: 10 | G2: =E2*F2 -> 20000
A3: 45598 | B3: SH003 | C3: =VLOOKUP($B3, 商品マスタ!$A:$D, 2, FALSE) -> 食品 | D3: =VLOOKUP($B3, 商品マスタ!$A:$D, 3, FALSE) -> チョコレート | E3: =VLOOKUP($B3, 商品マスタ!$A:$D, 4, FALSE) -> 500 | F3: 13 | G3: =E3*F3 -> 6500
A4: 45599 | B4: SH005 | C4: =VLOOKUP($B4, 商品マスタ!$A:$D, 2, FALSE) -> スポーツ用品 | D4: =VLOOKUP($B4, 商品マスタ!$A:$D, 3, FALSE) -> ランニングシューズ | E4: =VLOOKUP($B4, 商品マスタ!$A:$D, 4, FALSE) -> 12000 | F4: 8 | G4: =E4*F4 -> 96000
A5: 45600 | B5: SH002 | C5: =VLOOKUP($B5, 商品マスタ!$A:$D, 2, FALSE) -> 家電 | D5: =VLOOKUP($B5, 商品マスタ!$A:$D, 3, FALSE) -> ヘッドホン | E5: =VLOOKUP($B5, 商品マスタ!$A:$D, 4, FALSE) -> 8000 | F5: 15 | G5: =E5*F5 -> 120000
A6: 45601 | B6: SH004 | C6: =VLOOKUP($B6, 商品マスタ!$A:$D, 2, FALSE) -> 文房具 | D6: =VLOOKUP($B6, 商品マスタ!$A:$D, 3, FALSE) -> ボールペン | E6: =VLOOKUP($B6, 商品マスタ!$A:$D, 4, FALSE) -> 100 | F6: 12 | G6: =E6*F6 -> 1200
A7: 45602 | B7: SH001 | C7: =VLOOKUP($B7, 商品マスタ!$A:$D, 2, FALSE) -> ファッション | D7: =VLOOKUP($B7, 商品マスタ!$A:$D, 3, FALSE) -> Tシャツ | E7: =VLOOKUP($B7, 商品マスタ!$A:$D, 4, FALSE) -> 2000 | F7: 10 | G7: =E7*F7 -> 20000
A8: 45603 | B8: SH004 | C8: =VLOOKUP($B8, 商品マスタ!$A:$D, 2, FALSE) -> 文房具 | D8: =VLOOKUP($B8, 商品マスタ!$A:$D, 3, FALSE) -> ボールペン | E8: =VLOOKUP($B8, 商品マスタ!$A:$D, 4, FALSE) -> 100 | F8: 9 | G8: =E8*F8 -> 900
A9: 45604 | B9: SH005 | C9: =VLOOKUP($B9, 商品マスタ!$A:$D, 2, FALSE) -> スポーツ用品 | D9: =VLOOKUP($B9, 商品マスタ!$A:$D, 3, FALSE) -> ランニングシューズ | E9: =VLOOKUP($B9, 商品マスタ!$A:$D, 4, FALSE) -> 12000 | F9: 14 | G9: =E9*F9 -> 168000
A10: 45605 | B10: SH002 | C10: =VLOOKUP($B10, 商品マスタ!$A:$D, 2, FALSE) -> 家電 | D10: =VLOOKUP($B10, 商品マスタ!$A:$D, 3, FALSE) -> ヘッドホン | E10: =VLOOKUP($B10, 商品マスタ!$A:$D, 4, FALSE) -> 8000 | F10: 11 | G10: =E10*F10 -> 88000
A11: 45606 | B11: SH003 | C11: =VLOOKUP($B11, 商品マスタ!$A:$D, 2, FALSE) -> 食品 | D11: =VLOOKUP($B11, 商品マスタ!$A:$D, 3, FALSE) -> チョコレート | E11: =VLOOKUP($B11, 商品マスタ!$A:$D, 4, FALSE) -> 500 | F11: 13 | G11: =E11*F11 -> 6500

Sheet 商品マスタ
A1: 商品ID | B1: 商品カテゴリー | C1: 商品名 | D1: 単価
A2: SH001 | B2: ファッション | C2: Tシャツ | D2: 2000
A3: SH002 | B3: 家電 | C3: ヘッドホン | D3: 8000
A4: SH003 | B4: 食品 | C4: チョコレート | D4: 500
A5: SH004 | B5: 文房具 | C5: ボールペン | D5: 100
A6: SH005 | B6: スポーツ用品 | C6: ランニングシューズ | D6: 12000

Sheet SUMIF
A1: 売上日 | B1: 商品名 | C1: 売上 | E1: 商品名 | F1: 売上合計
A2: 45597 | B2: Tシャツ | C2: 20000 | E2: {=_xlfn.UNIQUE(B2:B11)} -> Tシャツ | F2: =SUMIF($B$2:$B$11, E2, $C$2:$C$11) -> 40000
A3: 45598 | B3: ヘッドホン | C3: 104000 | E3: ヘッドホン | F3: =SUMIF($B$2:$B$11, E3, $C$2:$C$11) -> 192000
A4: 45599 | B4: チョコレート | C4: 4000 | E4: チョコレート | F4: =SUMIF($B$2:$B$11, E4, $C$2:$C$11) -> 10500
A5: 45600 | B5: ボールペン | C5: 1500 | E5: ボールペン | F5: =SUMIF($B$2:$B$11, E5, $C$2:$C$11) -> 2400
A6: 45601 | B6: ランニングシューズ | C6: 144000 | E6: ランニングシューズ | F6: =SUMIF($B$2:$B$11, E6, $C$2:$C$11) -> 312000
A7: 45602 | B7: Tシャツ | C7: 20000
A8: 45603 | B8: ボールペン | C8: 900
A9: 45604 | B9: ランニングシューズ | C9: 168000
A10: 45605 | B10: ヘッドホン | C10: 88000
A11: 45606 | B11: チョコレート | C11: 6500

Sheet COUNTIF
A1: 売上日 | B1: 商品名 | D1: 商品名 | E1: 販売個数
A2: 45597 | B2: Tシャツ | D2: {=_xlfn.UNIQUE(B2:B11)} -> Tシャツ | E2: =COUNTIF($B$2:$B$11, D2) -> 3
A3: 45598 | B3: ヘッドホン | D3: ヘッドホン | E3: =COUNTIF($B$2:$B$11, D3) -> 2
A4: 45599 | B4: Tシャツ | D4: ボールペン | E4: =COUNTIF($B$2:$B$11, D4) -> 2
A5: 45600 | B5: ボールペン | D5: ランニングシューズ | E5: =COUNTIF($B$2:$B$11, D5) -> 2
A6: 45601 | B6: ランニングシューズ | D6: チョコレート | E6: =COUNTIF($B$2:$B$11, D6) -> 1
A7: 45602 | B7: Tシャツ
A8: 45603 | B8: ボールペン
A9: 45604 | B9: ランニングシューズ
A10: 45605 | B10: ヘッドホン
A11: 45606 | B11: チョコレート

Sheet グラフ化
A1: 売上日 | B1: 商品名 | C1: 個数 | D1: 売上 | F1: 商品名 | G1: 売上
A2: 45597 | B2: Tシャツ | C2: 30 | D2: 20000 | F2: {=_xlfn.UNIQUE(B2:B11)} -> Tシャツ | G2: =SUMIF($B$2:$B$11, F2, $D$2:$D$11) -> 40000
A3: 45598 | B3: ヘッドホン | C3: 20 | D3: 104000 | F3: ヘッドホン | G3: =SUMIF($B$2:$B$11, F3, $D$2:$D$11) -> 192000
A4: 45599 | B4: チョコレート | C4: 25 | D4: 4000 | F4: チョコレート | G4: =SUMIF($B$2:$B$11, F4, $D$2:$D$11) -> 10500
A5: 45600 | B5: ボールペン | C5: 13 | D5: 1500 | F5: ボールペン | G5: =SUMIF($B$2:$B$11, F5, $D$2:$D$11) -> 2400
A6: 45601 | B6: ランニングシューズ | C6: 14 | D6: 144000 | F6: ランニングシューズ | G6: =SUMIF($B$2:$B$11, F6, $D$2:$D$11) -> 312000
A7: 45602 | B7: Tシャツ | C7: 28 | D7: 20000
A8: 45603 | B8: ボールペン | C8: 18 | D8: 900
A9: 45604 | B9: ランニングシューズ | C9: 30 | D9: 168000
A10: 45605 | B10: ヘッドホン | C10: 15 | D10: 88000
A11: 45606 | B11: チョコレート | C11: 18 | D11: 6500

Sheet テーブル化
A1: 売上日 | B1: 商品名 | C1: 個数 | D1: 売上 | E1: 税込み
A2: 45597 | B2: Tシャツ | C2: 30 | D2: 20000 | E2: =テーブル1[[#This Row],[売上]]*1.1 -> 22000
A3: 45598 | B3: ヘッドホン | C3: 20 | D3: 104000 | E3: =テーブル1[[#This Row],[売上]]*1.1 -> 114400
A4: 45599 | B4: チョコレート | C4: 25 | D4: 4000 | E4: =テーブル1[[#This Row],[売上]]*1.1 -> 4400
A5: 45600 | B5: ボールペン | C5: 13 | D5: 1500 | E5: =テーブル1[[#This Row],[売上]]*1.1 -> 1650
A6: 45601 | B6: ランニングシューズ | C6: 14 | D6: 144000 | E6: =テーブル1[[#This Row],[売上]]*1.1 -> 158400
A7: 45602 | B7: Tシャツ | C7: 28 | D7: 20000 | E7: =テーブル1[[#This Row],[売上]]*1.1 -> 22000
A8: 45603 | B8: ボールペン | C8: 18 | D8: 900 | E8: =テーブル1[[#This Row],[売上]]*1.1 -> 990
A9: 45604 | B9: ランニングシューズ | C9: 30 | D9: 168000 | E9: =テーブル1[[#This Row],[売上]]*1.1 -> 184800
A10: 45605 | B10: ヘッドホン | C10: 15 | D10: 88000 | E10: =テーブル1[[#This Row],[売上]]*1.1 -> 96800
A11: 45606 | B11: チョコレート | C11: 18 | D11: 6500 | E11: =テーブル1[[#This Row],[売上]]*1.1 -> 7150
A12: 45607 | B12: ランニングシューズ | C12: 20 | D12: 104000 | E12: =テーブル1[[#This Row],[売上]]*1.1 -> 114400
A13: 46338 | B13: 消しゴム | E13: =テーブル1[[#This Row],[売上]]*1.1 -> 0

Sheet 商品一覧
A1: 商品名
A2: Tシャツ
A3: ヘッドホン
A4: チョコレート
A5: ボールペン
A6: ランニングシューズ
A7: 消しゴム
A8: ラインレシーバー

Sheet スライサー
A1: 売上日 | B1: カテゴリー | C1: 商品名 | D1: 個数 | E1: 売上 | F1: 担当者
A2: 45597 | B2: ファッション | C2: Tシャツ | D2: 30 | E2: 20000 | F2: 田中
A3: 45598 | B3: 家電 | C3: ヘッドホン | D3: 20 | E3: 104000 | F3: 鈴木
A4: 45599 | B4: 食品 | C4: チョコレート | D4: 25 | E4: 4000 | F4: 佐藤
A5: 45600 | B5: 文房具 | C5: ボールペン | D5: 13 | E5: 1500 | F5: 田中
A6: 45601 | B6: スポーツ用品 | C6: ランニングシューズ | D6: 14 | E6: 144000 | F6: 鈴木
A7: 45602 | B7: ファッション | C7: Tシャツ | D7: 28 | E7: 20000 | F7: 佐藤
A8: 45603 | B8: 文房具 | C8: ボールペン | D8: 18 | E8: 900 | F8: 田中
A9: 45604 | B9: スポーツ用品 | C9: ランニングシューズ | D9: 30 | E9: 168000 | F9: 鈴木
A10: 45605 | B10: 家電 | C10: ヘッドホン | D10: 15 | E10: 88000 | F10: 佐藤
A11: 45606 | B11: 食品 | C11: チョコレート | D11: 18 | E11: 6500 | F11: 田中
A12: 集計 | E12: =SUBTOTAL(109,T_売上データ[売上]) -> 556900 | F12: =SUBTOTAL(103,T_売上データ[担当者]) -> 10
